Metadata-Version: 1.1
Name: imdbsearch
Version: 1.0
Summary: Given a name, imbdsearch queries IMDB and returns a list of movies that individual has appeared in
Home-page: https://github.com/Anightingale/imdb-actor-search
Author: UNKNOWN
Author-email: UNKNOWN
License: UNKNOWN
Download-URL: https://github.com/Anightingale/imdb-actor-search/archive/1.0.tar.gz
Keywords: tag1,tag2
Platform: UNKNOWN
